{"config": {"view": {"continuousWidth": 400, "continuousHeight": 300}}, "data": {"name": "data-ef073a89db2e8bc265e5d5f1b5a7b658"}, "mark": "bar", "encoding": {"tooltip": [{"type": "quantitative", "field": "Month"}, {"type": "quantitative", "field": "size"}], "x": {"type": "quantitative", "field": "Month"}, "y": {"type": "quantitative", "field": "size"}}, "height": 400, "title": "2020 ridership by month", "width": 400, "$schema": "https://vega.github.io/schema/vega-lite/v4.8.1.json", "datasets": {"data-ef073a89db2e8bc265e5d5f1b5a7b658": [{"Month": 1.0, "size": 124335}, {"Month": 2.0, "size": 128642}, {"Month": 3.0, "size": 90851}, {"Month": 4.0, "size": 44213}, {"Month": 5.0, "size": 70895}, {"Month": 6.0, "size": 79900}, {"Month": 7.0, "size": 83530}, {"Month": 8.0, "size": 85360}, {"Month": 9.0, "size": 84178}, {"Month": 10.0, "size": 101529}, {"Month": 11.0, "size": 82244}]}}